{".class": "MypyFile", "_fullname": "crypto", "_name": null, "is_stub": false, "names": {".class": "SymbolTable", "Optional": {".class": "SymbolTableNode", "cross_ref": "typing.Optional", "kind": "Gdef"}, "PrivateKey": {".class": "SymbolTableNode", "kind": "Gdef", "node": {".class": "TypeInfo", "_promote": null, "abstract_attributes": [], "bases": ["builtins.object"], "declared_metaclass": null, "defn": {".class": "ClassDef", "fullname": "crypto.PrivateKey", "name": "PrivateKey", "type_vars": []}, "flags": [], "fullname": "crypto.PrivateKey", "metaclass_type": null, "metadata": {}, "module_name": "crypto", "mro": ["crypto.PrivateKey", "builtins.object"], "names": {".class": "SymbolTable", "__init__": {".class": "SymbolTableNode", "kind": "Mdef", "node": {".class": "FuncDef", "arg_kinds": [0, 0], "arg_names": ["self", "n"], "flags": [], "fullname": "crypto.PrivateKey.__init__", "name": "__init__", "type": {".class": "CallableType", "arg_kinds": [0, 0], "arg_names": ["self", "n"], "arg_types": ["crypto.PrivateKey", "builtins.int"], "bound_args": [], "def_extras": {"first_arg": "self"}, "fallback": "builtins.function", "implicit": false, "is_classmethod_class": false, "is_ellipsis_args": false, "name": "__init__ of PrivateKey", "ret_type": {".class": "NoneTyp"}, "variables": []}}}, "n": {".class": "SymbolTableNode", "implicit": true, "kind": "Mdef", "node": {".class": "Var", "flags": [], "fullname": "crypto.PrivateKey.n", "name": "n", "type": "builtins.int"}}, "public_key": {".class": "SymbolTableNode", "kind": "Mdef", "node": {".class": "FuncDef", "arg_kinds": [0], "arg_names": ["self"], "flags": [], "fullname": "crypto.PrivateKey.public_key", "name": "public_key", "type": {".class": "CallableType", "arg_kinds": [0], "arg_names": ["self"], "arg_types": ["crypto.PrivateKey"], "bound_args": [], "def_extras": {"first_arg": "self"}, "fallback": "builtins.function", "implicit": false, "is_classmethod_class": false, "is_ellipsis_args": false, "name": "public_key of PrivateKey", "ret_type": "crypto.PublicKey", "variables": []}}}, "sign": {".class": "SymbolTableNode", "kind": "Mdef", "node": {".class": "FuncDef", "arg_kinds": [0, 0], "arg_names": ["self", "message"], "flags": [], "fullname": "crypto.PrivateKey.sign", "name": "sign", "type": {".class": "CallableType", "arg_kinds": [0, 0], "arg_names": ["self", "message"], "arg_types": ["crypto.PrivateKey", {".class": "AnyType", "missing_import_name": null, "source_any": null, "type_of_any": "unannotated"}], "bound_args": [], "def_extras": {"first_arg": "self"}, "fallback": "builtins.function", "implicit": false, "is_classmethod_class": false, "is_ellipsis_args": false, "name": "sign of PrivateKey", "ret_type": "builtins.str", "variables": []}}}}, "tuple_type": null, "type_vars": [], "typeddict_type": null}}, "PublicKey": {".class": "SymbolTableNode", "kind": "Gdef", "node": {".class": "TypeInfo", "_promote": null, "abstract_attributes": [], "bases": ["builtins.object"], "declared_metaclass": null, "defn": {".class": "ClassDef", "fullname": "crypto.PublicKey", "name": "PublicKey", "type_vars": []}, "flags": [], "fullname": "crypto.PublicKey", "metaclass_type": null, "metadata": {}, "module_name": "crypto", "mro": ["crypto.PublicKey", "builtins.object"], "names": {".class": "SymbolTable", "__init__": {".class": "SymbolTableNode", "kind": "Mdef", "node": {".class": "FuncDef", "arg_kinds": [0, 0], "arg_names": ["self", "n"], "flags": [], "fullname": "crypto.PublicKey.__init__", "name": "__init__", "type": {".class": "CallableType", "arg_kinds": [0, 0], "arg_names": ["self", "n"], "arg_types": ["crypto.PublicKey", {".class": "UnionType", "items": ["builtins.int", "builtins.bytes"]}], "bound_args": [], "def_extras": {"first_arg": "self"}, "fallback": "builtins.function", "implicit": false, "is_classmethod_class": false, "is_ellipsis_args": false, "name": "__init__ of PublicKey", "ret_type": {".class": "NoneTyp"}, "variables": []}}}, "n": {".class": "SymbolTableNode", "implicit": true, "kind": "Mdef", "node": {".class": "Var", "flags": [], "fullname": "crypto.PublicKey.n", "name": "n", "type": "builtins.int"}}, "to_bytes": {".class": "SymbolTableNode", "kind": "Mdef", "node": {".class": "FuncDef", "arg_kinds": [0], "arg_names": ["self"], "flags": [], "fullname": "crypto.PublicKey.to_bytes", "name": "to_bytes", "type": {".class": "CallableType", "arg_kinds": [0], "arg_names": ["self"], "arg_types": ["crypto.PublicKey"], "bound_args": [], "def_extras": {"first_arg": "self"}, "fallback": "builtins.function", "implicit": false, "is_classmethod_class": false, "is_ellipsis_args": false, "name": "to_bytes of PublicKey", "ret_type": "builtins.bytes", "variables": []}}}, "verify": {".class": "SymbolTableNode", "kind": "Mdef", "node": {".class": "FuncDef", "arg_kinds": [0, 0, 0], "arg_names": ["self", "signature", "message"], "flags": [], "fullname": "crypto.PublicKey.verify", "name": "verify", "type": null}}}, "tuple_type": null, "type_vars": [], "typeddict_type": null}}, "Union": {".class": "SymbolTableNode", "cross_ref": "typing.Union", "kind": "Gdef"}, "__doc__": {".class": "SymbolTableNode", "kind": "Gdef", "node": {".class": "Var", "flags": [], "fullname": "crypto.__doc__", "name": "__doc__", "type": "builtins.str"}}, "__file__": {".class": "SymbolTableNode", "kind": "Gdef", "node": {".class": "Var", "flags": [], "fullname": "crypto.__file__", "name": "__file__", "type": "builtins.str"}}, "__name__": {".class": "SymbolTableNode", "kind": "Gdef", "node": {".class": "Var", "flags": [], "fullname": "crypto.__name__", "name": "__name__", "type": "builtins.str"}}, "__package__": {".class": "SymbolTableNode", "kind": "Gdef", "node": {".class": "Var", "flags": [], "fullname": "crypto.__package__", "name": "__package__", "type": "builtins.str"}}}, "path": "/home/guilherme/projects/crypto/src/crypto.py"}
