{"id": "json", "path": "/usr/lib/mypy/typeshed/stdlib/3/json/__init__.pyi", "mtime": 1513361034, "size": 1813, "hash": "395ddd55e79877a2a52ebd58dd44bf16", "data_mtime": 1528567316, "dependencies": ["sys", "typing", "json.decoder", "json.encoder", "builtins"], "suppressed": [], "child_modules": ["json.decoder", "json.encoder"], "options": {"disallow_any_expr": false, "disallow_subclassing_any": false, "follow_imports": "normal", "ignore_missing_imports": false, "disallow_any_generics": false, "strict_optional": false, "no_implicit_optional": false, "warn_no_return": true, "strict_boolean": false, "ignore_errors": false, "strict_optional_whitelist": null, "show_none_errors": true, "disallow_untyped_defs": false, "quick_and_dirty": false, "warn_return_any": false, "platform": "linux", "disallow_any_unimported": false, "disallow_untyped_decorators": false, "check_untyped_defs": false, "disallow_untyped_calls": false, "disallow_any_explicit": false, "disallow_any_decorated": false}, "dep_prios": [10, 5, 5, 5, 5], "interface_hash": "03e776a885f132eb58ebb23dfcfbb610", "version_id": "0.560", "ignore_all": false}
